{
  "Version": "1.0",
  "ServerInfo": {
    "Server1": {
      "IP": "127.0.0.1",
      "Port": "2302",
      "Name": "LOCAL"
    },
    "Server2": {
      "IP": "189.127.165.103",
      "Port": "2302",
      "Name": "RefúgioZ"
    }
  },
"ExistingMods": [
  "@CF",
  "@DabsFramework",
  "@DayZ-Expansion-Core",
  "@DayZ-Expansion-Chat",
  "@DayZ-Expansion-Name-Tags",
  "@DayZ-Expansion-Navigation",
  "@DayZ-Expansion-Spawn-Selection",
  "@DayZ-Expansion-Groups",
  "@BuildStackX3",
  "@BaseBuildingPlus",
  "@BBPItemPack",
  "@CodeLock",
  "@MMG-Base-Storage",
  "@C4RaidOnly",
  "@Backpack",
  "@CarPack",
  "@RepairMyCar",
  "@FT-Promocodes-FREE",
  "@MZ-KOTH",
  "@Stryker_Admin_Clothing",
  "@DayZ-Expansion-Book",
  "@DayZ-Expansion",
  "@TerritoryPlus",
  "@VPPAdminTools"
],
"Mods": [
  {
    "FileName": "Mods/@DayZ-Expansion-Book.zip",
    "Size": 37463513,
    "MD5": "3F88850CD547CF39161C31ED38CE37EC",
    "DownloadUrl": "https://github.com/RustFamily/refugioz-mods-update/releases/download/v1.0/@DayZ-Expansion-Book.zip"
  },
  {
    "FileName": "Mods/@DayZ-Expansion-Navigation.zip",
    "Size": 1401355,
    "MD5": "9476F0DA47A94F8454159F327A02D0B1",
    "DownloadUrl": "https://github.com/RustFamily/refugioz-mods-update/releases/download/v1.0/@DayZ-Expansion-Navigation.zip"
  },
  {
    "FileName": "Mods/@Basic.Territories.zip",
    "Size": 64766,
    "MD5": "3B1B5A969C9A9475D13AAA4D8782AA3E",
    "DownloadUrl": "https://github.com/RustFamily/refugioz-mods-update/releases/download/v1.0/@Basic.Territories.zip"
  },
  {
    "FileName": "Mods/@QuickMoveItemsByCategory.zip",
    "Size": 837883,
    "MD5": "EB7E484955BF2CE7C03DAE975507FA92",
    "DownloadUrl": "https://github.com/RustFamily/refugioz-mods-update/releases/download/v1.0/@QuickMoveItemsByCategory.zip"
  },
  {
    "FileName": "Mods/@DayZ-Expansion.zip",
    "Size": 109561056,
    "MD5": "DE3A45A1B28D5388C1668FC676B8BF09",
    "DownloadUrl": "https://github.com/RustFamily/refugioz-mods-update/releases/download/v1.0/@DayZ-Expansion.zip"
  }
]
}
